mlchem/__init__.py
mlchem/potentials.py
mlchem/utils.py
mlchem/backends/__init__.py
mlchem/backends/available.py
mlchem/backends/operations.py
mlchem/data/__init__.py
mlchem/data/handler.py
mlchem/data/visualization.py
mlchem/fingerprints/__init__.py
mlchem/fingerprints/cutoff.py
mlchem/fingerprints/gaussian.py
mlchem/models/__init__.py
mlchem/models/neuralnetwork.py
mlchem-0.0.0.dist-info/LICENSE
mlchem-0.0.0.dist-info/METADATA
mlchem-0.0.0.dist-info/WHEEL
mlchem-0.0.0.dist-info/top_level.txt
mlchem-0.0.0.dist-info/RECORD
