Metadata-Version: 2.1
Name: mlchem
Version: 0.0.0
Summary: Machine learning for chemistry
Home-page: https://github.com/muammar/mlchem
Author: Muammar El Khatib
Author-email: muammarelkhatib@gmail.com
License: UNKNOWN
Platform: UNKNOWN
Classifier: Programming Language :: Python :: 3
Classifier: Operating System :: OS Independent
